femupy/__init__.py
femupy/main.py
femupy-0.1.4.dist-info/LICENSE
femupy-0.1.4.dist-info/METADATA
femupy-0.1.4.dist-info/WHEEL
femupy-0.1.4.dist-info/top_level.txt
femupy-0.1.4.dist-info/RECORD
