Metadata-Version: 2.2
Name: femupy
Version: 0.1.4
Summary: Finite element model updating using natural frequencies and mode shapes
Home-page: https://github.com/blazkurent/femupy
Author: Blaž Kurent
Author-email: blaz.kurent@fgg.uni-lj.si
Classifier: Programming Language :: Python :: 3
Classifier: License :: OSI Approved :: MIT License
Classifier: Operating System :: OS Independent
Classifier: Development Status :: 3 - Alpha
License-File: LICENSE
Requires-Dist: numpy
Requires-Dist: pandas
Requires-Dist: seaborn
Requires-Dist: matplotlib
Requires-Dist: tensorflow
Requires-Dist: scikit-learn
Requires-Dist: scipy
Requires-Dist: SALib
Requires-Dist: pymoo
Dynamic: author
Dynamic: author-email
Dynamic: classifier
Dynamic: description
Dynamic: description-content-type
Dynamic: home-page
Dynamic: requires-dist
Dynamic: summary
